greyhorse_redis/__init__.py
greyhorse_redis/config.py
greyhorse_redis/contexts.py
greyhorse_redis/engine.py
greyhorse_redis/factory.py
greyhorse_redis/service.py
greyhorse_redis/translations.toml
greyhorse_redis-0.1.1.dist-info/METADATA
greyhorse_redis-0.1.1.dist-info/WHEEL
greyhorse_redis-0.1.1.dist-info/RECORD
